ppsmart/__init__.py
ppsmart/utils.py
ppsmart-0.0.2.dist-info/LICENSE
ppsmart-0.0.2.dist-info/METADATA
ppsmart-0.0.2.dist-info/WHEEL
ppsmart-0.0.2.dist-info/top_level.txt
ppsmart-0.0.2.dist-info/RECORD
