Metadata-Version: 2.1
Name: ppsmart
Version: 0.0.2
Summary: ppsmart packages utilities collection
Home-page: https://github.com/jakkritz/ppsmart_packages
Author: jakkrit s.
Author-email: jakkrit@ppsmartbot.com
License: UNKNOWN
Platform: UNKNOWN
Classifier: Programming Language :: Python :: 3
Classifier: License :: OSI Approved :: MIT License
Classifier: Operating System :: OS Independent
